pyatoa/__init__.py
pyatoa/core/__init__.py
pyatoa/core/config.py
pyatoa/core/executive.py
pyatoa/core/inspector.py
pyatoa/core/manager.py
pyatoa/scripts/__init__.py
pyatoa/scripts/data_data_example.py
pyatoa/scripts/load_example_data.py
pyatoa/scripts/process_data_w_mpi.py
pyatoa/scripts/syn_syn_example.py
pyatoa/tests/__init__.py
pyatoa/tests/test_asdf_utils.py
pyatoa/tests/test_config.py
pyatoa/tests/test_executive.py
pyatoa/tests/test_inspector.py
pyatoa/tests/test_manager.py
pyatoa/tests/test_mgmt_plot.py
pyatoa/tests/test_process_util.py
pyatoa/tests/test_utils.py
pyatoa/tests/test_wave_maker.py
pyatoa/utils/__init__.py
pyatoa/utils/adjoint.py
pyatoa/utils/calculate.py
pyatoa/utils/form.py
pyatoa/utils/images.py
pyatoa/utils/process.py
pyatoa/utils/srcrcv.py
pyatoa/utils/window.py
pyatoa/utils/write.py
pyatoa/utils/asdf/__init__.py
pyatoa/utils/asdf/add.py
pyatoa/utils/asdf/clean.py
pyatoa/utils/asdf/load.py
pyatoa/utils/asdf/write.py
pyatoa/visuals/__init__.py
pyatoa/visuals/insp_plot.py
pyatoa/visuals/map_maker.py
pyatoa/visuals/wave_maker.py
pyatoa/visuals/wave_train.py
pyatoa-0.4.2.dist-info/LICENSE.txt
pyatoa-0.4.2.dist-info/METADATA
pyatoa-0.4.2.dist-info/WHEEL
pyatoa-0.4.2.dist-info/top_level.txt
pyatoa-0.4.2.dist-info/RECORD
