Metadata-Version: 2.1
Name: pyatoa
Version: 0.4.2
Summary: Python's Adjoint Tomography Operations Assistant
Author: adjTomo Dev Team
Author-email: adjtomo@gmail.com
License: GNU GENERAL PUBLIC LICENSE
Project-URL: homepage, https://github.com/adjtomo/
Project-URL: documentation, https://pyatoa.readthedocs.io
Project-URL: repository, https://github.com/adjtomo/pyatoa
Requires-Python: >=3.7
License-File: LICENSE.txt
Requires-Dist: obspy
Requires-Dist: pyasdf
Requires-Dist: pandas
Requires-Dist: cartopy
Requires-Dist: pyyaml
Requires-Dist: pypdf
Requires-Dist: pyflex
Requires-Dist: pyadjoint
Provides-Extra: dev
Requires-Dist: pytest; extra == "dev"
Requires-Dist: ipython; extra == "dev"
Requires-Dist: ipdb; extra == "dev"
Provides-Extra: test
Requires-Dist: pytest; extra == "test"
